save_and_restore_api/__init__.py
save_and_restore_api/_api_async.py
save_and_restore_api/_api_base.py
save_and_restore_api/_api_threads.py
save_and_restore_api/_version.py
save_and_restore_api/_version.pyi
save_and_restore_api/py.typed
save_and_restore_api/aio/__init__.py
save_and_restore_api/tools/cli.py
save_and_restore_api-0.1.0.dist-info/licenses/LICENSE
save_and_restore_api-0.1.0.dist-info/METADATA
save_and_restore_api-0.1.0.dist-info/WHEEL
save_and_restore_api-0.1.0.dist-info/entry_points.txt
save_and_restore_api-0.1.0.dist-info/top_level.txt
save_and_restore_api-0.1.0.dist-info/RECORD
